tno/mpc/encryption_schemes/bgv/__init__.py
tno/mpc/encryption_schemes/bgv/bgv.py
tno/mpc/encryption_schemes/bgv/lattice_utils.py
tno/mpc/encryption_schemes/bgv/py.typed
tno/mpc/encryption_schemes/bgv/test/__init__.py
tno/mpc/encryption_schemes/bgv/test/const.py
tno/mpc/encryption_schemes/bgv/test/test_bgv.py
tno/mpc/encryption_schemes/bgv/test/test_equality.py
tno/mpc/encryption_schemes/bgv/test/test_keygen.py
tno/mpc/encryption_schemes/bgv/test/test_lattice_utils.py
tno/mpc/encryption_schemes/bgv/test/test_serialization.py
tno_mpc_encryption_schemes_bgv-0.1.1.dist-info/licenses/LICENSE
tno_mpc_encryption_schemes_bgv-0.1.1.dist-info/METADATA
tno_mpc_encryption_schemes_bgv-0.1.1.dist-info/WHEEL
tno_mpc_encryption_schemes_bgv-0.1.1.dist-info/top_level.txt
tno_mpc_encryption_schemes_bgv-0.1.1.dist-info/RECORD
