Metadata-Version: 2.4
Name: tno.mpc.encryption_schemes.bgv
Version: 0.1.1
Summary: Implementation of the additive part of the BGV homomorphic encryption scheme.
Author-email: TNO PET Lab <petlab@tno.nl>
Maintainer-email: TNO PET Lab <petlab@tno.nl>
License: Apache License, Version 2.0
Project-URL: Homepage, https://pet.tno.nl/
Project-URL: Documentation, https://docs.pet.tno.nl/mpc/encryption_schemes/bgv/0.1.1
Project-URL: Source, https://github.com/TNO-MPC/encryption_schemes.bgv
Keywords: TNO,MPC,multi-party computation,cryptosystem,encryption scheme,homomorphic encryption,post-quantum cryptography,RLWE,BGV
Platform: any
Classifier: License :: OSI Approved :: Apache Software License
Classifier: Programming Language :: Python :: 3
Classifier: Operating System :: OS Independent
Classifier: Intended Audience :: Developers
Classifier: Intended Audience :: Information Technology
Classifier: Intended Audience :: Science/Research
Classifier: Typing :: Typed
Classifier: Topic :: Security :: Cryptography
Requires-Python: >=3.9
License-File: LICENSE
Requires-Dist: tno.mpc.encryption_schemes.templates~=4.0
Requires-Dist: tno.mpc.encryption_schemes.utils~=0.15.0
Provides-Extra: gmpy
Requires-Dist: tno.mpc.encryption_schemes.utils[gmpy]; extra == "gmpy"
Provides-Extra: communication
Requires-Dist: tno.mpc.communication~=4.8.1; extra == "communication"
Provides-Extra: tests
Requires-Dist: tno.mpc.encryption_schemes.bgv[communication]; extra == "tests"
Requires-Dist: pytest>=8.1; extra == "tests"
Requires-Dist: pytest-asyncio; extra == "tests"
Dynamic: license-file
